{"doc":" 商品品牌Service业务层处理\n","fields":[],"enumConstants":[],"methods":[{"name":"queryById","paramTypes":["java.lang.Long"],"doc":" 查询商品品牌\n"},{"name":"queryPageList","paramTypes":["com.ruoyi.wms.domain.bo.ItemBrandBo","com.ruoyi.common.mybatis.core.page.PageQuery"],"doc":" 查询商品品牌列表\n"},{"name":"queryList","paramTypes":["com.ruoyi.wms.domain.bo.ItemBrandBo"],"doc":" 查询商品品牌列表\n"},{"name":"insertByBo","paramTypes":["com.ruoyi.wms.domain.bo.ItemBrandBo"],"doc":" 新增商品品牌\n"},{"name":"updateByBo","paramTypes":["com.ruoyi.wms.domain.bo.ItemBrandBo"],"doc":" 修改商品品牌\n"},{"name":"deleteById","paramTypes":["java.lang.Long"],"doc":" 批量删除商品品牌\n"}],"constructors":[]}